pinkbelt/__init__.py
pinkbelt/circle.py
pinkbelt/config.py
pinkbelt/configure.py
pinkbelt/dependencies.py
pinkbelt/deployment.py
pinkbelt/errors.py
pinkbelt/git.py
pinkbelt/handle_github.py
pinkbelt/handle_trello.py
pinkbelt/messages.py
pinkbelt/notify.py
pinkbelt/slack.py
pinkbelt/tasks.py
pinkbelt/version.py
pinkbelt/apis/__init__.py
pinkbelt/apis/trello.py
pinkbelt/commands/__init__.py
pinkbelt/commands/dep.py
pinkbelt/commands/gh.py
pinkbelt/commands/init.py
pinkbelt/commands/production.py
pinkbelt/commands/rollback.py
pinkbelt/commands/slack.py
pinkbelt/commands/stage.py
pinkbelt/commands/t.py
pinkbelt/commands/version.py
pinkbelt-0.16.1.data/scripts/bb
pinkbelt-0.16.1.dist-info/LICENSE
pinkbelt-0.16.1.dist-info/METADATA
pinkbelt-0.16.1.dist-info/WHEEL
pinkbelt-0.16.1.dist-info/top_level.txt
pinkbelt-0.16.1.dist-info/RECORD
